dm_dbcore/DatabaseConnection.py
dm_dbcore/__init__.py
dm_dbcore/adapters/__init__.py
dm_dbcore/adapters/postgresql/__init__.py
dm_dbcore/adapters/postgresql/ast_pg_geometry.py
dm_dbcore/adapters/postgresql/numpy_postgresql.py
dm_dbcore/adapters/postgresql/numpy_postgresql_psycopg2.py
dm_dbcore/adapters/postgresql/pgcitext.py
dm_dbcore/adapters/postgresql/pggeometry.py
dm_dbcore/adapters/sqlite/__init__.py
dm_dbcore/adapters/sqlite/numpy_sqlite.py
dm_dbcore/mysql/__init__.py
dm_dbcore/mysql/mysql_utils.py
dm_dbcore-0.1.0.dist-info/licenses/LICENSE
dm_dbcore-0.1.0.dist-info/METADATA
dm_dbcore-0.1.0.dist-info/WHEEL
dm_dbcore-0.1.0.dist-info/top_level.txt
dm_dbcore-0.1.0.dist-info/RECORD
