Metadata-Version: 2.4
Name: dm-dbcore
Version: 0.1.0
Summary: SQLAlchemy database connection wrapper with metadata caching and multi-database support
Home-page: https://github.com/demitri/dm-dbcore
Author: Demitri Muna
Author-email: Demitri Muna <pypi@nightlightresearch.com>
License: BSD-3-Clause
Project-URL: Homepage, https://github.com/demitri/dm-dbcore
Project-URL: Bug Reports, https://github.com/demitri/dm-dbcore/issues
Project-URL: Source, https://github.com/demitri/dm-dbcore
Keywords: sqlalchemy,database,postgresql,mysql,sqlite,orm
Classifier: Development Status :: 3 - Alpha
Classifier: Intended Audience :: Developers
Classifier: Topic :: Database
Classifier: Topic :: Software Development :: Libraries :: Python Modules
Classifier: License :: OSI Approved :: BSD License
Classifier: Programming Language :: Python :: 3
Classifier: Programming Language :: Python :: 3.8
Classifier: Programming Language :: Python :: 3.9
Classifier: Programming Language :: Python :: 3.10
Classifier: Programming Language :: Python :: 3.11
Classifier: Programming Language :: Python :: 3.12
Requires-Python: >=3.8
License-File: LICENSE
Requires-Dist: sqlalchemy>=2.0.0
Provides-Extra: postgresql
Requires-Dist: psycopg[binary]>=3.0; extra == "postgresql"
Provides-Extra: mysql
Requires-Dist: pymysql>=1.0.0; extra == "mysql"
Provides-Extra: numpy
Requires-Dist: numpy>=1.20.0; extra == "numpy"
Provides-Extra: astronomy
Requires-Dist: numpy>=1.20.0; extra == "astronomy"
Requires-Dist: cornish; extra == "astronomy"
Provides-Extra: dev
Requires-Dist: pytest>=7.0; extra == "dev"
Requires-Dist: black; extra == "dev"
Requires-Dist: flake8; extra == "dev"
Dynamic: author
Dynamic: home-page
Dynamic: license-file
Dynamic: requires-python
